riecovest/__init__.py
riecovest/covariance_estimation.py
riecovest/distance.py
riecovest/matrix_operations.py
riecovest/random_matrices.py
riecovest-0.0.4.dist-info/licenses/LICENSE
riecovest-0.0.4.dist-info/METADATA
riecovest-0.0.4.dist-info/WHEEL
riecovest-0.0.4.dist-info/top_level.txt
riecovest-0.0.4.dist-info/RECORD
