Metadata-Version: 2.4
Name: riecovest
Version: 0.0.4
Author-email: Jesper Brunnström <jesper_brunnstrom@hotmail.com>
Project-URL: Documentation, https://sounds-research.github.io/riecovest/
Project-URL: Repository, https://github.com/SOUNDS-RESEARCH/riecovest
Classifier: Operating System :: OS Independent
Classifier: Programming Language :: Python :: 3
Classifier: License :: OSI Approved :: MIT License
Requires-Python: >=3.11
License-File: LICENSE
Requires-Dist: numpy
Requires-Dist: scipy
Requires-Dist: jax
Requires-Dist: pymanopt
Requires-Dist: aspcore
Provides-Extra: examples
Requires-Dist: pandas; extra == "examples"
Requires-Dist: soundfile; extra == "examples"
Requires-Dist: seaborn; extra == "examples"
Requires-Dist: seaborn_qqplot; extra == "examples"
Requires-Dist: matplotlib; extra == "examples"
Requires-Dist: samplerate; extra == "examples"
Dynamic: license-file
